pso_load_flow/__init__.py
pso_load_flow/calculo.py
pso_load_flow/load_flows.py
pso_load_flow/pso.py
pso_load_flow-0.1.0.dist-info/METADATA
pso_load_flow-0.1.0.dist-info/WHEEL
pso_load_flow-0.1.0.dist-info/RECORD
