Metadata-Version: 2.1
Name: pso-load-flow
Version: 0.1.0
Summary: 
Author: Danilo Nascimento
Author-email: daconnas.dcn@gmail.com
Requires-Python: >=3.10.6,<4.0.0
Classifier: Programming Language :: Python :: 3
Classifier: Programming Language :: Python :: 3.11
Requires-Dist: numpy (>=1.24.2,<2.0.0)
Requires-Dist: pandas (>=1.5.3,<2.0.0)
